Workbook
Name Aporte: app!$D$19
Name patrimonio: app!$D$22
Name qtd_anos: app!$D$20
Name Rendimento_carteira: app!$D$15
Name salario: app!$D$14
Name sugestao_investimento: app!$D$16
Name taxa_mensal: app!$D$21

Sheet app
B13: CONFIGURAÇÕES
B14: Salário | D14: 5000
B15: Rendimento Carteira | D15: 0.0089
B16: Sugestão Investimento (30%) | D16: =salario*30% -> 1500
B18: INVESTIMENTO MENSAL
B19: Quanto Investir por mês? | D19: 1500
B20: Por quantos anos ? | D20: 5
B21: Taxa de Rendimento Mensal? | D21: 0.01079
B22: Patrimônio acumulado? | D22: =FV(taxa_mensal,qtd_anos*12,Aporte*-1) -> 125665.37
B23: Dividendos mensais? | D23: =D22*Rendimento_carteira -> 1118.4218
B25: CENÁRIOS | D25: Dividendo
A26: 2 | B26: Quanto em 2 anos? | C26: =FV($D$21,$A26*12,$D$19*-1) -> 40841.441 | D26: =C26*Rendimento_carteira -> 363.48882
A27: 5 | B27: Quanto em 5 anos? | C27: =FV($D$21,$A27*12,$D$19*-1) -> 125665.37 | D27: =C27*Rendimento_carteira -> 1118.4218
A28: 10 | B28: Quanto em 10 anos? | C28: =FV($D$21,$A28*12,$D$19*-1) -> 364926.32 | D28: =C28*Rendimento_carteira -> 3247.8442
A29: 20 | B29: Quanto em 20 anos? | C29: =FV($D$21,$A29*12,$D$19*-1) -> 1687797.6 | D29: =C29*Rendimento_carteira -> 15021.399
A30: 30 | B30: Quanto em 30 anos? | C30: =FV($D$21,$A30*12,$D$19*-1) -> 6483254.5 | D30: =C30*Rendimento_carteira -> 57700.965
B32: PERFIL | C32: Conservador
B33: VALOR A SER INVESTIDO POR MÊS | C33: =Aporte -> 1500
B35: TIPO DE FII | C35: Percentual sugerido | D35: Valores
B36: PAPEL | C36: =VLOOKUP($C$32&"-"&B36,tbl_apoio!$B$3:$E$21,4,FALSE) -> 0.3 | D36: =C36*$C$33 -> 450
B37: TIJOLO | C37: =VLOOKUP($C$32&"-"&B37,tbl_apoio!$B$3:$E$21,4,FALSE) -> 0.5 | D37: =C37*$C$33 -> 750
B38: HÍBRIDOS | C38: =VLOOKUP($C$32&"-"&B38,tbl_apoio!$B$3:$E$21,4,FALSE) -> 0.1 | D38: =C38*$C$33 -> 150
B39: FOFs | C39: =VLOOKUP($C$32&"-"&B39,tbl_apoio!$B$3:$E$21,4,FALSE) -> 0.1 | D39: =C39*$C$33 -> 150
B40: DESENVOLVIMENTO | C40: =VLOOKUP($C$32&"-"&B40,tbl_apoio!$B$3:$E$21,4,FALSE) -> 0 | D40: =C40*$C$33 -> 0
B41: HOTELARIAS | C41: =VLOOKUP($C$32&"-"&B41,tbl_apoio!$B$3:$E$21,4,FALSE) -> 0 | D41: =C41*$C$33 -> 0
D42: =SUM(D36:D41) -> 1500

Sheet tbl_apoio
B3: CHAVE | C3: PERFIL | D3: TIPO DE FII | E3: %
B4: =$C$4&"-"&D4 -> Conservador-PAPEL | C4: Conservador | D4: PAPEL | E4: 0.3
B5: =$C$4&"-"&D5 -> Conservador-TIJOLO | C5: Conservador | D5: TIJOLO | E5: 0.5
B6: =$C$4&"-"&D6 -> Conservador-HÍBRIDOS | C6: Conservador | D6: HÍBRIDOS | E6: 0.1
B7: =$C$4&"-"&D7 -> Conservador-FOFs | C7: Conservador | D7: FOFs | E7: 0.1
B8: =$C$4&"-"&D8 -> Conservador-DESENVOLVIMENTO | C8: Conservador | D8: DESENVOLVIMENTO | E8: 0
B9: =$C$4&"-"&D9 -> Conservador-HOTELARIAS | C9: Conservador | D9: HOTELARIAS | E9: 0
B10: =$C$10&"-"&D10 -> Moderado-PAPEL | C10: Moderado | D10: PAPEL | E10: 0.32
B11: =$C$10&"-"&D11 -> Moderado-TIJOLO | C11: Moderado | D11: TIJOLO | E11: 0.35
B12: =$C$10&"-"&D12 -> Moderado-HÍBRIDOS | C12: Moderado | D12: HÍBRIDOS | E12: 0.08
B13: =$C$10&"-"&D13 -> Moderado-FOFs | C13: Moderado | D13: FOFs | E13: 0.05
B14: =$C$10&"-"&D14 -> Moderado-DESENVOLVIMENTO | C14: Moderado | D14: DESENVOLVIMENTO | E14: 0.1
B15: =$C$10&"-"&D15 -> Moderado-HOTELARIAS | C15: Moderado | D15: HOTELARIAS | E15: 0.1
B16: =$C$16&"-"&D16 -> Agressivo-PAPEL | C16: Agressivo | D16: PAPEL | E16: 0.5
B17: =$C$16&"-"&D17 -> Agressivo-TIJOLO | C17: Agressivo | D17: TIJOLO | E17: 0.1
B18: =$C$16&"-"&D18 -> Agressivo-HÍBRIDOS | C18: Agressivo | D18: HÍBRIDOS | E18: 0.05
B19: =$C$16&"-"&D19 -> Agressivo-FOFs | C19: Agressivo | D19: FOFs | E19: 0.05
B20: =$C$16&"-"&D20 -> Agressivo-DESENVOLVIMENTO | C20: Agressivo | D20: DESENVOLVIMENTO | E20: 0.2
B21: =$C$16&"-"&D21 -> Agressivo-HOTELARIAS | C21: Agressivo | D21: HOTELARIAS | E21: 0.1
